pystratum_middle/BulkHandler.py
pystratum_middle/__init__.py
pystratum_middle/exception/ResultException.py
pystratum_middle/exception/__init__.py
pystratum_middle-1.2.0.dist-info/LICENSE.md
pystratum_middle-1.2.0.dist-info/METADATA
pystratum_middle-1.2.0.dist-info/WHEEL
pystratum_middle-1.2.0.dist-info/RECORD
