Metadata-Version: 2.1
Name: PyStratum-Middle
Version: 1.2.0
Summary: PyStratum Middle: The glue between a PyStratum backend and your application
Home-page: https://github.com/DatabaseStratum/py-stratum-middle
License: MIT
Keywords: PyStratum,Middle
Author: Set Based IT Consultancy
Author-email: info@setbased.nl
Requires-Python: >=3.12.0,<4.0.0
Classifier: Development Status :: 5 - Production/Stable
Classifier: Intended Audience :: Developers
Classifier: License :: OSI Approved :: MIT License
Classifier: Programming Language :: Python :: 3
Classifier: Programming Language :: Python :: 3.12
Classifier: Topic :: Software Development :: Build Tools
Classifier: Topic :: Software Development :: Code Generators
Classifier: Topic :: System :: Installation/Setup
Project-URL: Documentation, https://stratum.readthedocs.io/
Project-URL: Repository, https://github.com/DatabaseStratum/py-stratum-middle
